popmon/__init__.py
popmon/config.py
popmon/resources.py
popmon/utils.py
popmon/version.py
popmon/alerting/__init__.py
popmon/alerting/alerts_summary.py
popmon/alerting/compute_tl_bounds.py
popmon/analysis/__init__.py
popmon/analysis/apply_func.py
popmon/analysis/functions.py
popmon/analysis/hist_numpy.py
popmon/analysis/merge_statistics.py
popmon/analysis/comparison/__init__.py
popmon/analysis/comparison/comparisons.py
popmon/analysis/comparison/hist_comparer.py
popmon/analysis/profiling/__init__.py
popmon/analysis/profiling/hist_profiler.py
popmon/analysis/profiling/profiles.py
popmon/analysis/profiling/pull_calculator.py
popmon/base/__init__.py
popmon/base/module.py
popmon/base/pipeline.py
popmon/base/registry.py
popmon/decorators/__init__.py
popmon/decorators/pandas.py
popmon/decorators/spark.py
popmon/extensions/__init__.py
popmon/extensions/extension.py
popmon/extensions/profile_diptest.py
popmon/hist/__init__.py
popmon/hist/hist_splitter.py
popmon/hist/hist_utils.py
popmon/hist/filling/__init__.py
popmon/io/__init__.py
popmon/io/file_reader.py
popmon/io/file_writer.py
popmon/io/json_reader.py
popmon/notebooks/__init__.py
popmon/notebooks/popmon_tutorial_advanced.ipynb
popmon/notebooks/popmon_tutorial_basic.ipynb
popmon/notebooks/popmon_tutorial_incremental_data.ipynb
popmon/notebooks/popmon_tutorial_reports.ipynb
popmon/pipeline/__init__.py
popmon/pipeline/amazing_pipeline.py
popmon/pipeline/dataset_splitter.py
popmon/pipeline/metrics.py
popmon/pipeline/metrics_pipelines.py
popmon/pipeline/report.py
popmon/pipeline/report_pipelines.py
popmon/pipeline/timing.py
popmon/stats/__init__.py
popmon/stats/numpy.py
popmon/stitching/__init__.py
popmon/stitching/hist_stitcher.py
popmon/test_data/__init__.py
popmon/test_data/data_generator_hists.json.gz
popmon/test_data/example.json
popmon/test_data/example_histogram.json
popmon/test_data/flight_delays.csv.gz
popmon/test_data/flight_delays_reference.csv.gz
popmon/test_data/synthetic_histograms.json
popmon-1.4.12.dist-info/licenses/LICENSE
popmon-1.4.12.dist-info/licenses/NOTICE
popmon-1.4.12.dist-info/METADATA
popmon-1.4.12.dist-info/WHEEL
popmon-1.4.12.dist-info/entry_points.txt
popmon-1.4.12.dist-info/top_level.txt
popmon-1.4.12.dist-info/RECORD
