Metadata-Version: 2.4
Name: popmon
Version: 1.4.12
Summary: Monitor the stability of a pandas or spark dataset
Author-email: ING Analytics Wholesale Banking <wbaa@ing.com>
License: Copyright 2023 ING Analytics Wholesale Banking
Project-URL: repository, https://github.com/ing-bank/popmon
Keywords: pandas,spark,data-science,data-analysis,monitoring,statistics,python,jupyter,ipython
Classifier: Programming Language :: Python :: 3
Classifier: License :: OSI Approved :: MIT License
Classifier: Operating System :: OS Independent
Requires-Python: >=3.9
License-File: LICENSE
License-File: NOTICE
Requires-Dist: numpy>=1.18.0
Requires-Dist: pandas>=0.25.1
Requires-Dist: scipy>=1.5.2
Requires-Dist: histogrammar>=1.1.2
Requires-Dist: phik
Requires-Dist: jinja2
Requires-Dist: tqdm
Requires-Dist: plotly
Requires-Dist: joblib>=0.14.0
Requires-Dist: htmlmin2
Requires-Dist: pydantic>=2
Requires-Dist: pydantic-settings
Requires-Dist: typing_extensions
Provides-Extra: test
Requires-Dist: pytest>=4.0.2; extra == "test"
Requires-Dist: pytest-notebook>=0.6.1; extra == "test"
Requires-Dist: jupyter_client>=5.2.3; extra == "test"
Requires-Dist: ipykernel>=5.1.3; extra == "test"
Requires-Dist: pre-commit>=2.9.0; extra == "test"
Provides-Extra: diptest
Requires-Dist: diptest; extra == "diptest"
Dynamic: license-file
